ubidump.py
ubidump-1.0.0.dist-info/LICENSE
ubidump-1.0.0.dist-info/METADATA
ubidump-1.0.0.dist-info/WHEEL
ubidump-1.0.0.dist-info/entry_points.txt
ubidump-1.0.0.dist-info/top_level.txt
ubidump-1.0.0.dist-info/RECORD
